sqldb/__init__.py
sqldb/helpers.py
sqldb/sql_db.py
tests/__init__.py
tests/test_sql_db.py
sql_oprations-0.0.3.dist-info/LICENSE
sql_oprations-0.0.3.dist-info/METADATA
sql_oprations-0.0.3.dist-info/WHEEL
sql_oprations-0.0.3.dist-info/top_level.txt
sql_oprations-0.0.3.dist-info/RECORD
