Metadata-Version: 2.1
Name: sql-oprations
Version: 0.0.3
Summary: this package is use for sql CRUD operations on sql database.
Home-page: UNKNOWN
Author: Sachin Indoriya
Author-email: sachinindoriya63@gmail.com
License: UNKNOWN
Keywords: python
Platform: UNKNOWN
Classifier: Development Status :: 1 - Planning
Classifier: Intended Audience :: Developers
Classifier: Programming Language :: Python :: 3
Classifier: Operating System :: Unix
Classifier: Operating System :: MacOS :: MacOS X
Classifier: Operating System :: Microsoft :: Windows
License-File: LICENSE
Requires-Dist: mysql-connector-python
